metar_taf_parser/__init__.py
metar_taf_parser/command/__init__.py
metar_taf_parser/command/common.py
metar_taf_parser/command/metar.py
metar_taf_parser/command/remark.py
metar_taf_parser/command/taf.py
metar_taf_parser/commons/__init__.py
metar_taf_parser/commons/converter.py
metar_taf_parser/commons/exception.py
metar_taf_parser/commons/i18n.py
metar_taf_parser/locale/messages.pot
metar_taf_parser/locale/de/LC_MESSAGES/messages.mo
metar_taf_parser/locale/de/LC_MESSAGES/messages.po
metar_taf_parser/locale/en/LC_MESSAGES/messages.mo
metar_taf_parser/locale/en/LC_MESSAGES/messages.po
metar_taf_parser/locale/es/LC_MESSAGES/messages.mo
metar_taf_parser/locale/es/LC_MESSAGES/messages.po
metar_taf_parser/locale/fr/LC_MESSAGES/messages.mo
metar_taf_parser/locale/fr/LC_MESSAGES/messages.po
metar_taf_parser/locale/it/LC_MESSAGES/messages.mo
metar_taf_parser/locale/it/LC_MESSAGES/messages.po
metar_taf_parser/locale/pl/LC_MESSAGES/messages.mo
metar_taf_parser/locale/pl/LC_MESSAGES/messages.po
metar_taf_parser/locale/ru-RU/LC_MESSAGES/messages.mo
metar_taf_parser/locale/ru-RU/LC_MESSAGES/messages.po
metar_taf_parser/locale/tr/LC_MESSAGES/messages.mo
metar_taf_parser/locale/tr/LC_MESSAGES/messages.po
metar_taf_parser/locale/zh-CN/LC_MESSAGES/messages.mo
metar_taf_parser/locale/zh-CN/LC_MESSAGES/messages.po
metar_taf_parser/model/__init__.py
metar_taf_parser/model/enum.py
metar_taf_parser/model/model.py
metar_taf_parser/parser/__init__.py
metar_taf_parser/parser/parser.py
metar_taf_parser_mivek-1.10.1.dist-info/licenses/LICENSE
node_modules/npm/node_modules/node-gyp/gyp/gyp_main.py
node_modules/npm/node_modules/node-gyp/gyp/test_gyp.py
node_modules/npm/node_modules/node-gyp/gyp/pylib/gyp/MSVSNew.py
node_modules/npm/node_modules/node-gyp/gyp/pylib/gyp/MSVSProject.py
node_modules/npm/node_modules/node-gyp/gyp/pylib/gyp/MSVSSettings.py
node_modules/npm/node_modules/node-gyp/gyp/pylib/gyp/MSVSSettings_test.py
node_modules/npm/node_modules/node-gyp/gyp/pylib/gyp/MSVSToolFile.py
metar_taf_parser_mivek-1.10.1.dist-info/METADATA
metar_taf_parser_mivek-1.10.1.dist-info/WHEEL
metar_taf_parser_mivek-1.10.1.dist-info/top_level.txt
metar_taf_parser_mivek-1.10.1.dist-info/RECORD
